nimbus_chart/__init__.py
nimbus_chart/admin.py
nimbus_chart/apps.py
nimbus_chart/constants.py
nimbus_chart/models.py
nimbus_chart/views.py
nimbus_chart/viewsets.py
nimbus_chart/chart/__init__.py
nimbus_chart/chart/echarts.py
nimbus_chart/chart/mixin.py
nimbus_chart/migrations/__init__.py
nimbus_chart/static/nimbus_chart/js/echarts.min.js
nimbus_chart/static/nimbus_chart/js/jquery-3.2.1.js
nimbus_chart/static/nimbus_chart/js/jquery-3.2.1.min.js
nimbus_chart/templates/nimbus_chart/base.html
nimbus_chart/templates/nimbus_chart/echarts.html
nimbus_chart-0.2.1.dist-info/DESCRIPTION.rst
nimbus_chart-0.2.1.dist-info/METADATA
nimbus_chart-0.2.1.dist-info/RECORD
nimbus_chart-0.2.1.dist-info/WHEEL
nimbus_chart-0.2.1.dist-info/metadata.json
nimbus_chart-0.2.1.dist-info/top_level.txt
