Metadata-Version: 2.0
Name: nimbus-chart
Version: 0.2.1
Summary: nimbus_chart
Home-page: https://github.com/williamren
Author: william
Author-email: william.ren@live.cn
License: Apache License 2.0
Keywords: nimbus_chart,nimbus,chart
Platform: Any
Classifier: Development Status :: 5 - Production/Stable
Classifier: Intended Audience :: Developers
Classifier: License :: OSI Approved :: Apache Software License
Classifier: Operating System :: MacOS :: MacOS X
Classifier: Operating System :: Microsoft :: Windows
Classifier: Operating System :: POSIX
Classifier: Programming Language :: Python
Classifier: Programming Language :: Python :: 2.7
Classifier: Programming Language :: Python :: 3
Classifier: Programming Language :: Python :: 3.3
Classifier: Programming Language :: Python :: 3.4
Classifier: Programming Language :: Python :: 3.5
Classifier: Programming Language :: Python :: 3.6
Classifier: Programming Language :: Python :: 3.7
Classifier: Environment :: Web Environment
Classifier: Framework :: Django
Classifier: Framework :: Django :: 1.8
Classifier: Framework :: Django :: 1.9
Classifier: Framework :: Django :: 1.10
Classifier: Framework :: Django :: 1.11
Classifier: Topic :: Internet :: WWW/HTTP
Requires-Dist: Django
Requires-Dist: jupyter-pip (>=0.3.1)
Requires-Dist: pyecharts (>=0.5.9)
Requires-Dist: pyecharts-javascripthon
